eth_docgen/__init__.py
eth_docgen/docgen.py
eth_docgen/data/doc.css
eth_docgen-0.1.3.dist-info/DESCRIPTION.rst
eth_docgen-0.1.3.dist-info/LICENSE.txt
eth_docgen-0.1.3.dist-info/METADATA
eth_docgen-0.1.3.dist-info/RECORD
eth_docgen-0.1.3.dist-info/WHEEL
eth_docgen-0.1.3.dist-info/entry_points.txt
eth_docgen-0.1.3.dist-info/metadata.json
eth_docgen-0.1.3.dist-info/top_level.txt
